t61codec.py
t61codec-1.0.1.dist-info/LICENSE
t61codec-1.0.1.dist-info/WHEEL
t61codec-1.0.1.dist-info/METADATA
t61codec-1.0.1.dist-info/RECORD
